vis3dvf/__init__.py
vis3dvf/plot.py
vis3dvf/vectorfield.py
vis3dvf-1.0.2.dist-info/LICENSE
vis3dvf-1.0.2.dist-info/METADATA
vis3dvf-1.0.2.dist-info/WHEEL
vis3dvf-1.0.2.dist-info/top_level.txt
vis3dvf-1.0.2.dist-info/RECORD
