Metadata-Version: 2.1
Name: vis3dvf
Version: 1.0.2
Summary: Derivative of vis3dpy, aimed at visualizing ℝ³ vector fields 
Home-page: https://github.com/LukasDrsman/vis3dvf
Author: Lukáš Dršman
Author-email: lukaskodr@gmail.com
License: Public Domain
Platform: UNKNOWN
Classifier: License :: Public Domain
Classifier: Programming Language :: Python :: 3
Classifier: Programming Language :: Python :: 3.7
License-File: LICENSE
Requires-Dist: numpy
Requires-Dist: pygame
Requires-Dist: PyOpenGL
Requires-Dist: PyOpenGL-accelerate
